mpy_kernel/__init__.py
mpy_kernel/__main__.py
mpy_kernel/install.py
mpy_kernel/kernel.py
mpy_kernel/mprepl.py
mpy_kernel/mprepl_hook.py
mpy_kernel/mprepl_utils.py
mpy_kernel/pyboard.py
jupyter_micropython_remote-1.4.dist-info/LICENSE
jupyter_micropython_remote-1.4.dist-info/METADATA
jupyter_micropython_remote-1.4.dist-info/WHEEL
jupyter_micropython_remote-1.4.dist-info/top_level.txt
jupyter_micropython_remote-1.4.dist-info/RECORD
