Metadata-Version: 2.1
Name: jupyter-micropython-remote
Version: 1.4
Summary: Jupyter notebook kernel for remote execution on a Micropython system.
Home-page: https://gitlab.com/alelec/jupyter_micropython_remote
Author: Andrew Leech, Julian Todd, Tony DiCola
Author-email: andrew@alelec.net
License: GPL3
Keywords: jupyter micropython
Platform: UNKNOWN
Requires-Dist: pyserial (>=3.4)
Requires-Dist: jupyter
Requires-Dist: mpy-cross
